LICENSE
MANIFEST.in
NEWS
README
README.rst
pdb-attach
pdb-clone
setup.cfg
setup.py
lib/__init__.py
lib/pdb_clone/__init__.py
lib/pdb_clone/_bdbmodule-py27.c
lib/pdb_clone/_bdbmodule-py3.c
lib/pdb_clone/_pdbhandler-py27.c
lib/pdb_clone/_pdbhandler-py3.c
lib/pdb_clone/attach.py
lib/pdb_clone/bdb.py
lib/pdb_clone/bootstrappdb_gdb.py
lib/pdb_clone/pdb.py
lib/pdb_clone/pdbhandler.py
lib/pdb_clone.egg-info/PKG-INFO
lib/pdb_clone.egg-info/SOURCES.txt
lib/pdb_clone.egg-info/dependency_links.txt
lib/pdb_clone.egg-info/top_level.txt
pdb-clone.wiki/News.wiki
pdb-clone.wiki/Performances.wiki
pdb-clone.wiki/ReadMe.wiki
pdb-clone.wiki/RemoteDebugging.wiki
python_patches/pdbhandler-py3.4.patch