Metadata-Version: 1.1
Name: pdb-clone
Version: 1.10.1
Summary: A clone of pdb, fast and with the remote debugging and attach features.
Home-page: https://github.com/corpusops/pdbclone.git
Author: Xavier de Gaye
Author-email: xdegaye@users.sourceforge.net
License: GNU GENERAL PUBLIC LICENSE Version 2
Platform: all
Classifier: Development Status :: 5 - Production/Stable
Classifier: Environment :: Console
Classifier: Intended Audience :: Developers
Classifier: License :: OSI Approved :: GNU General Public License v2 (GPLv2)
Classifier: Operating System :: Unix
Classifier: Programming Language :: Python :: 2
Classifier: Programming Language :: Python :: 3
Classifier: Topic :: Software Development :: Debuggers
